autocompile/__init__.py
tests/__init__.py
tests/test_main.py
autocompile-0.3.0.dist-info/LICENSE
autocompile-0.3.0.dist-info/METADATA
autocompile-0.3.0.dist-info/WHEEL
autocompile-0.3.0.dist-info/top_level.txt
autocompile-0.3.0.dist-info/RECORD
