Metadata-Version: 2.1
Name: autocompile
Version: 0.3.0
Summary: Speed up Python code that has well layed out type hints (works by converting the function to typed cython). Find more info at https://github.com/smpurkis/autocompile
Home-page: https://github.com/smpurkis/autocompile
Author: Sam Purkis
Author-email: sam.purkis@hotmail.co.uk
License: UNKNOWN
Project-URL: Bug Tracker, https://github.com/smpurkis/autocompile/issues
Platform: UNKNOWN
Classifier: Programming Language :: Python :: 3
Classifier: License :: OSI Approved :: MIT License
Classifier: Operating System :: OS Independent
Requires-Python: >=3.6
Requires-Dist: cython
Requires-Dist: numba
Requires-Dist: numpy
Requires-Dist: pytest
